pymcprotocol/__init__.py
pymcprotocol/mcprotocolconst.py
pymcprotocol/mcprotocolerror.py
pymcprotocol/type3e.py
pymcprotocol/type4e.py
pymcprotocol-0.2.9.dist-info/LICENSE
pymcprotocol-0.2.9.dist-info/WHEEL
pymcprotocol-0.2.9.dist-info/METADATA
pymcprotocol-0.2.9.dist-info/RECORD
