Metadata-Version: 2.1
Name: pymcprotocol
Version: 0.2.9
Summary: MC Protocol(MELSEC Communication Protocol) implementation by Python
Home-page: https://pymcprotocol.netlify.app/
License: MIT
Keywords: Mistubishi,PLC,factory
Author: Yohei Osawa
Author-email: yohei.osawa.318.niko8@gmail.com
Requires-Python: >=3.0,<4.0
Classifier: License :: OSI Approved :: MIT License
Classifier: Programming Language :: Python :: 3
Classifier: Programming Language :: Python :: 3.4
Classifier: Programming Language :: Python :: 3.5
Classifier: Programming Language :: Python :: 3.6
Classifier: Programming Language :: Python :: 3.7
Classifier: Programming Language :: Python :: 3.8
Classifier: Programming Language :: Python :: 3.9
Project-URL: Repository, https://github.com/senrust/pymcprotocol
